sqlescapy/__init__.py
sqlescapy/sqlescape.py
sqlescapy-1.0.1.dist-info/LICENSE
sqlescapy-1.0.1.dist-info/METADATA
sqlescapy-1.0.1.dist-info/WHEEL
sqlescapy-1.0.1.dist-info/top_level.txt
sqlescapy-1.0.1.dist-info/RECORD
