Metadata-Version: 2.1
Name: sqlescapy
Version: 1.0.1
Summary: Python module to escape SQL special characters and quotes in strings
Home-page: https://github.com/elouajib/sqlescapy
Author: Imad ElOuajib
Author-email: elouajib.im@gmail.com
License: UNKNOWN
Platform: UNKNOWN
Classifier: Programming Language :: Python :: 3
Classifier: License :: OSI Approved :: MIT License
Classifier: Operating System :: OS Independent
Requires-Python: >=2.7
